{
  "name": "League Script",
  "designer": "Haley Fiege",
  "license": "OFL",
  "visibility": "External",
  "category": "Handwriting",
  "size": 39623,
  "fonts": [
    {
      "name": "League Script",
      "style": "normal",
      "weight": 400,
      "filename": "LeagueScript.ttf",
      "postScriptName": "LeagueScript",
      "fullName": "League Script",
      "copyright": "Copyright (c) 2010, Haley Fiege (haley@kingdomofawesome.com)"
    }
  ],
  "subsets": [
    "latin",
    "menu"
  ],
  "dateAdded": "2011-03-09"
}
