{
    "processed": [
        {
            "file": {
                "name": "Roboto-BoldItalic.ttf",
                "type": "ttf",
                "size": 155748,
                "md5": "29adfde1242726defab9f5dd0fcb26af",
                "geometryMd5": "469483468dac72f0b885dc9d2eb5f33b"
            },
            "name": {
                "family": "Roboto",
                "subFamily": "Bold Italic",
                "fullName": "Roboto Bold Italic",
                "psName": "Roboto-BoldItalic",
                "versionText": "Version 3.002; 2020",
                "copyright": "Copyright 2011 Google Inc. All Rights Reserved.",
                "trademark": "Roboto is a trademark of Google.",
                "variationsPSNamePrefix": "Roboto"
            },
            "format": {
                "format": "OT",
                "flavor": "TT"
            },
            "summary": {
                "num_glyphs": 1295,
                "embedding": "Installable Embedding",
                "font_vendor_id": "GOOG",
                "font_vendor": "Google"
            },
            "validation": {
                "font_full_name": "Roboto Bold Italic",
                "level": "ERROR",
                "last_success": "finished validation python",
                "msg_count": {
                    "CRITICAL": 0,
                    "ERROR": 22,
                    "WARNING": 0,
                    "INFO": 0,
                    "DEBUG": 0
                },
                "result": [
                    {
                        "subroutine": "validate_63802aac57104d3aa48021e9210cb52a.hmtx",
                        "levelname": "ERROR",
                        "message": "The left sidebearing 56 does not match the glyph's xMin 57 (glyph 109)",
                        "timestamp": "2020-09-24T06:05:03.578133Z",
                        "orig_output": "validate_63802aac57104d3aa48021e9210cb52a.hmtx - ERROR - The left sidebearing 56 does not match the glyph's xMin 57 (glyph 109)",
                        "msg_code": "V0933"
                    },
                    {
                        "subroutine": "validate_63802aac57104d3aa48021e9210cb52a.hmtx",
                        "levelname": "ERROR",
                        "message": "The left sidebearing 182 does not match the glyph's xMin 181 (glyph 126)",
                        "timestamp": "2020-09-24T06:05:03.584438Z",
                        "orig_output": "validate_63802aac57104d3aa48021e9210cb52a.hmtx - ERROR - The left sidebearing 182 does not match the glyph's xMin 181 (glyph 126)",
                        "msg_code": "V0933"
                    },
                    {
                        "subroutine": "validate_63802aac57104d3aa48021e9210cb52a.hmtx",
                        "levelname": "ERROR",
                        "message": "The left sidebearing 187 does not match the glyph's xMin 186 (glyph 392)",
                        "timestamp": "2020-09-24T06:05:03.715169Z",
                        "orig_output": "validate_63802aac57104d3aa48021e9210cb52a.hmtx - ERROR - The left sidebearing 187 does not match the glyph's xMin 186 (glyph 392)",
                        "msg_code": "V0933"
                    },
                    {
                        "subroutine": "validate_63802aac57104d3aa48021e9210cb52a.hmtx",
                        "levelname": "ERROR",
                        "message": "The left sidebearing 120 does not match the glyph's xMin 119 (glyph 425)",
                        "timestamp": "2020-09-24T06:05:03.738443Z",
                        "orig_output": "validate_63802aac57104d3aa48021e9210cb52a.hmtx - ERROR - The left sidebearing 120 does not match the glyph's xMin 119 (glyph 425)",
                        "msg_code": "V0933"
                    },
                    {
                        "subroutine": "validate_63802aac57104d3aa48021e9210cb52a.hmtx",
                        "levelname": "ERROR",
                        "message": "The left sidebearing -89 does not match the glyph's xMin -90 (glyph 597)",
                        "timestamp": "2020-09-24T06:05:03.855478Z",
                        "orig_output": "validate_63802aac57104d3aa48021e9210cb52a.hmtx - ERROR - The left sidebearing -89 does not match the glyph's xMin -90 (glyph 597)",
                        "msg_code": "V0933"
                    },
                    {
                        "subroutine": "validate_63802aac57104d3aa48021e9210cb52a.hmtx",
                        "levelname": "ERROR",
                        "message": "The left sidebearing 230 does not match the glyph's xMin 231 (glyph 606)",
                        "timestamp": "2020-09-24T06:05:03.857360Z",
                        "orig_output": "validate_63802aac57104d3aa48021e9210cb52a.hmtx - ERROR - The left sidebearing 230 does not match the glyph's xMin 231 (glyph 606)",
                        "msg_code": "V0933"
                    },
                    {
                        "subroutine": "validate_63802aac57104d3aa48021e9210cb52a.hmtx",
                        "levelname": "ERROR",
                        "message": "The left sidebearing 172 does not match the glyph's xMin 173 (glyph 625)",
                        "timestamp": "2020-09-24T06:05:03.885125Z",
                        "orig_output": "validate_63802aac57104d3aa48021e9210cb52a.hmtx - ERROR - The left sidebearing 172 does not match the glyph's xMin 173 (glyph 625)",
                        "msg_code": "V0933"
                    },
                    {
                        "subroutine": "validate_63802aac57104d3aa48021e9210cb52a.hmtx",
                        "levelname": "ERROR",
                        "message": "The left sidebearing -87 does not match the glyph's xMin -86 (glyph 749)",
                        "timestamp": "2020-09-24T06:05:03.968255Z",
                        "orig_output": "validate_63802aac57104d3aa48021e9210cb52a.hmtx - ERROR - The left sidebearing -87 does not match the glyph's xMin -86 (glyph 749)",
                        "msg_code": "V0933"
                    },
                    {
                        "subroutine": "validate_63802aac57104d3aa48021e9210cb52a.hmtx",
                        "levelname": "ERROR",
                        "message": "The left sidebearing -5 does not match the glyph's xMin -4 (glyph 760)",
                        "timestamp": "2020-09-24T06:05:03.972247Z",
                        "orig_output": "validate_63802aac57104d3aa48021e9210cb52a.hmtx - ERROR - The left sidebearing -5 does not match the glyph's xMin -4 (glyph 760)",
                        "msg_code": "V0933"
                    },
                    {
                        "subroutine": "validate_63802aac57104d3aa48021e9210cb52a.hmtx",
                        "levelname": "ERROR",
                        "message": "The left sidebearing -98 does not match the glyph's xMin -97 (glyph 770)",
                        "timestamp": "2020-09-24T06:05:03.987024Z",
                        "orig_output": "validate_63802aac57104d3aa48021e9210cb52a.hmtx - ERROR - The left sidebearing -98 does not match the glyph's xMin -97 (glyph 770)",
                        "msg_code": "V0933"
                    },
                    {
                        "subroutine": "validate_63802aac57104d3aa48021e9210cb52a.hmtx",
                        "levelname": "ERROR",
                        "message": "The left sidebearing -132 does not match the glyph's xMin -131 (glyph 904)",
                        "timestamp": "2020-09-24T06:05:04.051461Z",
                        "orig_output": "validate_63802aac57104d3aa48021e9210cb52a.hmtx - ERROR - The left sidebearing -132 does not match the glyph's xMin -131 (glyph 904)",
                        "msg_code": "V0933"
                    },
                    {
                        "subroutine": "validate_63802aac57104d3aa48021e9210cb52a.hmtx",
                        "levelname": "ERROR",
                        "message": "The left sidebearing -129 does not match the glyph's xMin -128 (glyph 905)",
                        "timestamp": "2020-09-24T06:05:04.051914Z",
                        "orig_output": "validate_63802aac57104d3aa48021e9210cb52a.hmtx - ERROR - The left sidebearing -129 does not match the glyph's xMin -128 (glyph 905)",
                        "msg_code": "V0933"
                    },
                    {
                        "subroutine": "validate_63802aac57104d3aa48021e9210cb52a.hmtx",
                        "levelname": "ERROR",
                        "message": "The left sidebearing -127 does not match the glyph's xMin -126 (glyph 906)",
                        "timestamp": "2020-09-24T06:05:04.052348Z",
                        "orig_output": "validate_63802aac57104d3aa48021e9210cb52a.hmtx - ERROR - The left sidebearing -127 does not match the glyph's xMin -126 (glyph 906)",
                        "msg_code": "V0933"
                    },
                    {
                        "subroutine": "validate_63802aac57104d3aa48021e9210cb52a.hmtx",
                        "levelname": "ERROR",
                        "message": "The left sidebearing -20 does not match the glyph's xMin -19 (glyph 907)",
                        "timestamp": "2020-09-24T06:05:04.052786Z",
                        "orig_output": "validate_63802aac57104d3aa48021e9210cb52a.hmtx - ERROR - The left sidebearing -20 does not match the glyph's xMin -19 (glyph 907)",
                        "msg_code": "V0933"
                    },
                    {
                        "subroutine": "validate_63802aac57104d3aa48021e9210cb52a.hmtx",
                        "levelname": "ERROR",
                        "message": "The left sidebearing -116 does not match the glyph's xMin -115 (glyph 908)",
                        "timestamp": "2020-09-24T06:05:04.053248Z",
                        "orig_output": "validate_63802aac57104d3aa48021e9210cb52a.hmtx - ERROR - The left sidebearing -116 does not match the glyph's xMin -115 (glyph 908)",
                        "msg_code": "V0933"
                    },
                    {
                        "subroutine": "validate_63802aac57104d3aa48021e9210cb52a.hmtx",
                        "levelname": "ERROR",
                        "message": "The left sidebearing -10 does not match the glyph's xMin -11 (glyph 910)",
                        "timestamp": "2020-09-24T06:05:04.054044Z",
                        "orig_output": "validate_63802aac57104d3aa48021e9210cb52a.hmtx - ERROR - The left sidebearing -10 does not match the glyph's xMin -11 (glyph 910)",
                        "msg_code": "V0933"
                    },
                    {
                        "subroutine": "validate_63802aac57104d3aa48021e9210cb52a.hmtx",
                        "levelname": "ERROR",
                        "message": "The left sidebearing -80 does not match the glyph's xMin -79 (glyph 1164)",
                        "timestamp": "2020-09-24T06:05:04.136506Z",
                        "orig_output": "validate_63802aac57104d3aa48021e9210cb52a.hmtx - ERROR - The left sidebearing -80 does not match the glyph's xMin -79 (glyph 1164)",
                        "msg_code": "V0933"
                    },
                    {
                        "subroutine": "validate_63802aac57104d3aa48021e9210cb52a.hmtx",
                        "levelname": "ERROR",
                        "message": "The left sidebearing -139 does not match the glyph's xMin -140 (glyph 1183)",
                        "timestamp": "2020-09-24T06:05:04.141991Z",
                        "orig_output": "validate_63802aac57104d3aa48021e9210cb52a.hmtx - ERROR - The left sidebearing -139 does not match the glyph's xMin -140 (glyph 1183)",
                        "msg_code": "V0933"
                    },
                    {
                        "subroutine": "validate_63802aac57104d3aa48021e9210cb52a.hmtx",
                        "levelname": "ERROR",
                        "message": "The left sidebearing -99 does not match the glyph's xMin -98 (glyph 1232)",
                        "timestamp": "2020-09-24T06:05:04.159697Z",
                        "orig_output": "validate_63802aac57104d3aa48021e9210cb52a.hmtx - ERROR - The left sidebearing -99 does not match the glyph's xMin -98 (glyph 1232)",
                        "msg_code": "V0933"
                    },
                    {
                        "subroutine": "validate_63802aac57104d3aa48021e9210cb52a.hmtx",
                        "levelname": "ERROR",
                        "message": "The left sidebearing -200 does not match the glyph's xMin -199 (glyph 1233)",
                        "timestamp": "2020-09-24T06:05:04.160138Z",
                        "orig_output": "validate_63802aac57104d3aa48021e9210cb52a.hmtx - ERROR - The left sidebearing -200 does not match the glyph's xMin -199 (glyph 1233)",
                        "msg_code": "V0933"
                    },
                    {
                        "subroutine": "validate_63802aac57104d3aa48021e9210cb52a.name",
                        "levelname": "ERROR",
                        "message": "Postscript name not present for both Mac and Windows.",
                        "timestamp": "2020-09-24T06:05:16.031298Z",
                        "orig_output": "validate_63802aac57104d3aa48021e9210cb52a.name - ERROR - Postscript name not present for both Mac and Windows.",
                        "msg_code": "E2008"
                    },
                    {
                        "subroutine": "validate_63802aac57104d3aa48021e9210cb52a.OS_2.xAvgCharWidth",
                        "levelname": "ERROR",
                        "message": "The xAvgCharWidth should be 1153, but is 1161",
                        "timestamp": "2020-09-24T06:04:46.124048Z",
                        "orig_output": "validate_63802aac57104d3aa48021e9210cb52a.OS_2.xAvgCharWidth - ERROR - The xAvgCharWidth should be 1153, but is 1161",
                        "msg_code": "E2135"
                    }
                ]
            }
        }
    ],
    "skipped": [],
    "fontio3_version": "3.7.20200604.317848rc4",
    "fontvalidator_version": "20200305.1",
    "runningTime": 46597,
    "completedDate": "2020-09-24 06:05:25.776367"
}