{
  "name": "Nanum Pen Script",
  "designer": "Sandoll Communication",
  "license": "OFL",
  "visibility": "Sandbox",
  "category": "Handwriting",
  "size": 1548776,
  "fonts": [
    {
      "name": "Nanum Pen Script",
      "style": "normal",
      "weight": 400,
      "filename": "NanumPenScript-Regular.ttf",
      "postScriptName": "NanumPen",
      "fullName": "Nanum Pen",
      "copyright": "Copyright © 2010 NHN Corporation. All rights reserved. Font designed by Sandoll Communications Inc."
    }
  ],
  "subsets": [
    "korean",
    "menu"
  ],
  "dateAdded": "2012-05-09"
}
