{
  "name": "Happy Monkey",
  "designer": "Brenda Gallo",
  "license": "OFL",
  "visibility": "External",
  "category": "Display",
  "size": 40103,
  "fonts": [
    {
      "name": "Happy Monkey",
      "style": "normal",
      "weight": 400,
      "filename": "HappyMonkey-Regular.ttf",
      "postScriptName": "HappyMonkey-Regular",
      "fullName": "Happy Monkey",
      "copyright": "Copyright (c) 2011 by Brenda Gallo (gbrenda1987@gmail.com), with Reserved Font Name \"Happy Monkey\"."
    }
  ],
  "subsets": [
    "latin",
    "latin-ext",
    "menu"
  ],
  "dateAdded": "2012-03-14"
}
